Workbook

Sheet Pipeline
A1: CALM MONEY — Sales Pipeline
A2: ACTIVE: | B2: =COUNTIFS(A5:A80,"<>",F5:F80,"<>Closed-Won",F5:F80,"<>Closed-Lost") | C2: PIPELINE $: | D2: =SUMPRODUCT((F5:F80<>"Closed-Won")*(F5:F80<>"Closed-Lost")*(F5:F80<>"")*H5:H80) | F2: HOT: | G2: =COUNTIF(E5:E80,"Hot") | H2: OVERDUE: | I2: =COUNTIFS(K5:K80,"<"&TODAY(),K5:K80,"<>",F5:F80,"<>Closed-Won",F5:F80,"<>Closed-Lost") | J2: WON: | K2: =COUNTIF(F5:F80,"Closed-Won")
A4: Prospect | B4: Phone | C4: Email | D4: Source | E4: Priority | F4: Stage | G4: Product | H4: Est. Premium / AUM | I4: Est. Revenue | J4: First Contact | K4: Next Follow-Up | L4: Days Open | M4: Notes
A5: Sarah Johnson | B5: 519-555-0101 | C5: sarah.j@email.com | D5: Referral | E5: Hot | F5: Discovery Call | G5: Life Insurance + Wealth | H5: 350000 | I5: 4500 | J5: 2026-02-15 | K5: 2026-03-12 | L5: =IF(A5="","",DAYS(TODAY(),J5)) | M5: Couple, 2 kids. Needs term life + RRSP/TFSA strategy.
A6: David Chen | B6: 519-555-0202 | C6: d.chen@email.com | D6: Website | E6: Warm | F6: New Lead | G6: Wealth Management | H6: 180000 | I6: 1800 | J6: 2026-03-01 | K6: 2026-03-10 | L6: =IF(A6="","",DAYS(TODAY(),J6)) | M6: Software dev. Downloaded retirement guide.
A7: Jessica Williams | B7: 519-555-0303 | C7: jwilliams@email.com | D7: Social Media | E7: Hot | F7: Plan Presentation | G7: Life Insurance + Wealth | H7: 420000 | I7: 5200 | J7: 2026-01-20 | K7: 2026-03-14 | L7: =IF(A7="","",DAYS(TODAY(),J7)) | M7: Dual income. RESP + retirement + $1M term life.
A8: Michael Brown | B8: 519-555-0404 | C8: m.brown@email.com | D8: Seminar | E8: Warm | F8: Proposal Sent | G8: Wealth Management | H8: 275000 | I8: 2750 | J8: 2026-02-01 | K8: 2026-03-09 | L8: =IF(A8="","",DAYS(TODAY(),J8)) | M8: Business owner. Corp investing + personal.
A9: Priya Patel | B9: 519-555-0808 | C9: p.patel@email.com | D9: Referral | E9: Hot | F9: Negotiation | G9: Life Insurance + Wealth | H9: 850000 | I9: 10500 | J9: 2026-01-15 | K9: 2026-03-10 | L9: =IF(A9="","",DAYS(TODAY(),J9)) | M9: Physician. IPP, corp life, key person insurance.
A10: Amanda Taylor | B10: 519-555-0505 | C10: ataylor@email.com | D10: Referral | E10: Hot | F10: Closed-Won | G10: Wealth Management | H10: 500000 | I10: 5000 | J10: 2025-12-10 | L10: =IF(A10="","",DAYS(TODAY(),J10)) | M10: Full plan + investment mgmt. Great referral source.
A11: Tyler Brooks | B11: 519-555-0909 | C11: t.brooks@email.com | D11: Cold Outreach | E11: Cold | F11: Nurture | G11: Life Insurance | H11: 0 | I11: 1200 | J11: 2026-01-05 | K11: 2026-04-01 | L11: =IF(A11="","",DAYS(TODAY(),J11)) | M11: Young professional. Term life quote sent. Not ready for wealth.
A12: Vikas Sharma | F12: New Lead | H12: 250000 | J12: 2026-03-09 | L12: =IF(A12="","",DAYS(TODAY(),J12))
L13: =IF(A13="","",DAYS(TODAY(),J13))
L14: =IF(A14="","",DAYS(TODAY(),J14))
L15: =IF(A15="","",DAYS(TODAY(),J15))
L16: =IF(A16="","",DAYS(TODAY(),J16))
L17: =IF(A17="","",DAYS(TODAY(),J17))
L18: =IF(A18="","",DAYS(TODAY(),J18))
L19: =IF(A19="","",DAYS(TODAY(),J19))
L20: =IF(A20="","",DAYS(TODAY(),J20))
L21: =IF(A21="","",DAYS(TODAY(),J21))
L22: =IF(A22="","",DAYS(TODAY(),J22))
L23: =IF(A23="","",DAYS(TODAY(),J23))
L24: =IF(A24="","",DAYS(TODAY(),J24))
... L79: =IF(A79="","",DAYS(TODAY(),J79))

Sheet Dashboard
A1: PIPELINE DASHBOARD
A3: TOTAL PIPELINE | C3: EST. REVENUE | E3: WON REVENUE | G3: WIN RATE
A4: =SUMPRODUCT((Pipeline!F5:F80<>"Closed-Won")*(Pipeline!F5:F80<>"Closed-Lost")*(Pipeline!F5:F80<>"")*Pipeline!H5:H80) | C4: =SUMPRODUCT((Pipeline!F5:F80<>"Closed-Won")*(Pipeline!F5:F80<>"Closed-Lost")*(Pipeline!F5:F80<>"")*Pipeline!I5:I80) | E4: =SUMIF(Pipeline!F5:F80,"Closed-Won",Pipeline!I5:I80) | G4: =IFERROR(COUNTIF(Pipeline!F5:F80,"Closed-Won")/(COUNTIF(Pipeline!F5:F80,"Closed-Won")+COUNTIF(Pipeline!F5:F80,"Closed-Lost")),0)
A20: Stage | B20: Count | C20: Revenue
A21: New Lead | B21: =COUNTIF(Pipeline!F5:F80,A21) | C21: =SUMIF(Pipeline!F5:F80,A21,Pipeline!I5:I80)
A22: Contacted | B22: =COUNTIF(Pipeline!F5:F80,A22) | C22: =SUMIF(Pipeline!F5:F80,A22,Pipeline!I5:I80)
A23: Discovery Call | B23: =COUNTIF(Pipeline!F5:F80,A23) | C23: =SUMIF(Pipeline!F5:F80,A23,Pipeline!I5:I80)
A24: Needs Analysis | B24: =COUNTIF(Pipeline!F5:F80,A24) | C24: =SUMIF(Pipeline!F5:F80,A24,Pipeline!I5:I80)
A25: Plan Presentation | B25: =COUNTIF(Pipeline!F5:F80,A25) | C25: =SUMIF(Pipeline!F5:F80,A25,Pipeline!I5:I80)
A26: Proposal Sent | B26: =COUNTIF(Pipeline!F5:F80,A26) | C26: =SUMIF(Pipeline!F5:F80,A26,Pipeline!I5:I80)
A27: Negotiation | B27: =COUNTIF(Pipeline!F5:F80,A27) | C27: =SUMIF(Pipeline!F5:F80,A27,Pipeline!I5:I80)
A28: Closed-Won | B28: =COUNTIF(Pipeline!F5:F80,A28) | C28: =SUMIF(Pipeline!F5:F80,A28,Pipeline!I5:I80)
A29: Closed-Lost | B29: =COUNTIF(Pipeline!F5:F80,A29) | C29: =SUMIF(Pipeline!F5:F80,A29,Pipeline!I5:I80)
A30: Nurture | B30: =COUNTIF(Pipeline!F5:F80,A30) | C30: =SUMIF(Pipeline!F5:F80,A30,Pipeline!I5:I80)
A33: Source | B33: Count
A34: Referral | B34: =COUNTIF(Pipeline!D5:D80,A34)
A35: Website | B35: =COUNTIF(Pipeline!D5:D80,A35)
A36: Social Media | B36: =COUNTIF(Pipeline!D5:D80,A36)
A37: FOLLOW-UP STATUS
A38: Overdue Follow-Ups | D38: =COUNTIFS(Pipeline!K5:K80,"<"&TODAY(),Pipeline!K5:K80,"<>",Pipeline!F5:F80,"<>Closed-Won",Pipeline!F5:F80,"<>Closed-Lost")
A39: Due Today | D39: =COUNTIFS(Pipeline!K5:K80,TODAY(),Pipeline!F5:F80,"<>Closed-Won")
A40: Due This Week | D40: =COUNTIFS(Pipeline!K5:K80,">="&TODAY(),Pipeline!K5:K80,"<="&(TODAY()+7),Pipeline!F5:F80,"<>Closed-Won")
A41: Networking | B41: =COUNTIF(Pipeline!D5:D80,A41)
A42: Centre of Influence | B42: =COUNTIF(Pipeline!D5:D80,A42)
A45: Product | B45: Count | C45: Revenue
A46: Life Insurance | B46: =COUNTIF(Pipeline!G5:G80,A46) | C46: =SUMIF(Pipeline!G5:G80,A46,Pipeline!I5:I80)
A47: Wealth Management | B47: =COUNTIF(Pipeline!G5:G80,A47) | C47: =SUMIF(Pipeline!G5:G80,A47,Pipeline!I5:I80)
A48: Life Insurance + Wealth | B48: =COUNTIF(Pipeline!G5:G80,A48) | C48: =SUMIF(Pipeline!G5:G80,A48,Pipeline!I5:I80)
A49: Disability Insurance | B49: =COUNTIF(Pipeline!G5:G80,A49) | C49: =SUMIF(Pipeline!G5:G80,A49,Pipeline!I5:I80)
A50: Critical Illness | B50: =COUNTIF(Pipeline!G5:G80,A50) | C50: =SUMIF(Pipeline!G5:G80,A50,Pipeline!I5:I80)
A51: Group Benefits | B51: =COUNTIF(Pipeline!G5:G80,A51) | C51: =SUMIF(Pipeline!G5:G80,A51,Pipeline!I5:I80)

Sheet Activity Log
A1: DAILY ACTIVITY LOG
A2: Date | B2: Prospect | C2: What I Did | D2: Outcome | E2: Next Step | F2: Notes
A3: 2026-03-08 | B3: Priya Patel | C3: Video call - final proposal | D3: Reviewing with spouse | E3: Follow up Monday | F3: Key person insurance quote included
A4: 2026-03-07 | B4: Jessica Williams | C4: Presented full plan | D4: Loved it, wants to proceed | E4: Send engagement letter | F4: Adding $1M term life to plan
A5: 2026-03-05 | B5: Sarah Johnson | C5: Discovery call - 45 min | D5: Good fit, moving forward | E5: Send needs analysis | F5: Needs $500K term + RESP + RRSP
A6: 2026-03-01 | B6: David Chen | C6: Sent intro email | D6: Downloaded guide | E6: Call next week | F6: From website lead

Sheet Weekly Review
A1: MONDAY PIPELINE REVIEW
A3: THIS WEEK'S NUMBERS
A4: Active Deals | C4: =COUNTIFS(Pipeline!A5:A80,"<>",Pipeline!F5:F80,"<>Closed-Won",Pipeline!F5:F80,"<>Closed-Lost")
A5: Pipeline Value | C5: =SUMPRODUCT((Pipeline!F5:F80<>"Closed-Won")*(Pipeline!F5:F80<>"Closed-Lost")*(Pipeline!F5:F80<>"")*Pipeline!H5:H80)
A6: Hot Leads | C6: =COUNTIF(Pipeline!E5:E80,"Hot")
A7: Overdue Follow-Ups | C7: =COUNTIFS(Pipeline!K5:K80,"<"&TODAY(),Pipeline!K5:K80,"<>",Pipeline!F5:F80,"<>Closed-Won",Pipeline!F5:F80,"<>Closed-Lost")
A8: Follow-Ups This Week | C8: =COUNTIFS(Pipeline!K5:K80,">="&TODAY(),Pipeline!K5:K80,"<="&(TODAY()+7),Pipeline!F5:F80,"<>Closed-Won")
A9: Deals Won (Total) | C9: =COUNTIF(Pipeline!F5:F80,"Closed-Won")
A11: TOP 5 ACTIONS THIS WEEK
A12: Priority | B12: Action | C12: Prospect | D12: Done?
A19: WINS THIS WEEK
A24: NEXT WEEK'S FOCUS
A25: 1.
A26: 2.
A27: 3.
